{
    "启动妮姬": {
        "recognition": {
            "type": "DirectHit",
            "param": {}
        },
        "action": {
            "type": "DoNothing",
            "param": {}
        },
        "next": [
            "妮姬主页面",
            "启动妮姬app"
        ]
    },
    "启动妮姬app": {
        "recognition": {
            "type": "DirectHit",
            "param": {}
        },
        "action": {
            "type": "StartApp",
            "param": {
                "package": "com.tencent.nikke"
            }
        },
        "post_delay": 2000,
        "focus": "[color:green]启动妮姬app[/color]",
        "next": [
            "妮姬加载等待"
        ],
        "on_error": [
            "error"
        ]
    },
    "妮姬加载等待": {
        "recognition": {
            "type": "DirectHit",
            "param": {}
        },
        "action": {
            "type": "DoNothing",
            "param": {}
        },
        "post_delay": 5000,
        "focus": "[color:blue]妮姬加载等待[/color]",
        "next": [
            "妮姬公告",
            "QQ登陆",
            "妮姬下载",
            "妮姬点击开始",
            "妮姬加载等待"
        ]
    },
    "妮姬公告": {
        "recognition": {
            "type": "OCR",
            "param": {
                "expected": "公告",
                "roi": [
                    342,
                    246,
                    74,
                    60
                ]
            }
        },
        "action": {
            "type": "Click",
            "param": {
                "target": [
                    619,
                    259,
                    36,
                    35
                ]
            }
        },
        "post_wait_freezes": 1000,
        "focus": "[color:green]妮姬公告[/color]",
        "next": [
            "妮姬加载等待"
        ],
        "on_error": [
            "error"
        ]
    },
    "QQ登陆": {
        "recognition": {
            "type": "OCR",
            "param": {
                "expected": "与QQ好友玩",
                "roi": [
                    386,
                    966,
                    255,
                    78
                ]
            }
        },
        "action": {
            "type": "Click",
            "param": {}
        },
        "post_wait_freezes": 1000,
        "focus": "[color:green]QQ登陆[/color]",
        "next": [
            "妮姬加载等待"
        ],
        "on_error": [
            "error"
        ]
    },
    "妮姬下载": {
        "recognition": {
            "type": "OCR",
            "param": {
                "expected": "下载",
                "roi": [
                    318,
                    504,
                    85,
                    64
                ]
            }
        },
        "action": {
            "type": "Click",
            "param": {
                "target": [
                    342,
                    800,
                    75,
                    57
                ]
            }
        },
        "post_wait_freezes": 1000,
        "focus": "[color:green]妮姬下载[/color]",
        "next": [
            "妮姬加载等待"
        ],
        "on_error": [
            "error"
        ]
    },
    "妮姬模拟器主页面": {
        "recognition": {
            "type": "TemplateMatch",
            "param": {
                "template": "模拟器主页面.png",
                "roi": [
                    896,
                    60,
                    51,
                    42
                ]
            }
        },
        "action": {
            "type": "DoNothing",
            "param": {}
        },
        "next": [
            "启动妮姬"
        ]
    },
    "妮姬点击开始": {
        "recognition": {
            "type": "OCR",
            "param": {
                "expected": "点击开始",
                "roi": [
                    261,
                    967,
                    180,
                    96
                ]
            }
        },
        "action": {
            "type": "Click",
            "param": {}
        },
        "post_wait_freezes": 1000,
        "focus": "[color:green]妮姬点击开始[/color]",
        "next": [
            "妮姬进入主页面等待"
        ]
    },
    "妮姬进入主页面等待": {
        "recognition": {
            "type": "DirectHit",
            "param": {}
        },
        "action": {
            "type": "DoNothing",
            "param": {}
        },
        "post_delay": 2000,
        "focus": "[color:blue]妮姬进入主页面等待[/color]",
        "next": [
            "妮姬主页面公告",
            "妮姬主页面"
        ]
    },
    "妮姬主页面公告": {
        "recognition": {
            "type": "OCR",
            "param": {
                "expected": "公告",
                "roi": [
                    349,
                    107,
                    64,
                    45
                ]
            }
        },
        "action": {
            "type": "Click",
            "param": {
                "target": [
                    632,
                    112,
                    43,
                    36
                ]
            }
        },
        "focus": "[color:green]妮姬主页面公告[/color]",
        "next": [
            "妮姬主页面"
        ]
    },
    "妮姬主页面": {
        "recognition": {
            "type": "OCR",
            "param": {
                "expected": "大厅",
                "roi": [
                    318,
                    1206,
                    87,
                    59
                ]
            }
        },
        "action": {
            "type": "DoNothing",
            "param": {}
        },
        "focus": "[color:green]妮姬主页面[/color]"
    }
}